LICENSE.txt
README.md
aws_parquet/__init__.py
aws_parquet/_types.py
aws_parquet/dataset.py
aws_parquet/interface.py
aws_parquet/py.typed
aws_parquet-0.5.0.dist-info/LICENSE.txt
aws_parquet-0.5.0.dist-info/METADATA
aws_parquet-0.5.0.dist-info/WHEEL
aws_parquet-0.5.0.dist-info/RECORD
